alpha_factory/__init__.py
alpha_factory/backtest.py
alpha_factory/basic_functions.py
alpha_factory/bt_summary.py
alpha_factory/check_mem.py
alpha_factory/check_validation.py
alpha_factory/cprint.py
alpha_factory/df_gen.py
alpha_factory/factor_gen.py
alpha_factory/generator_core.py
alpha_factory/global_func.py
alpha_factory/ic_summary.py
alpha_factory/prepepare.py
alpha_factory/utilise.py
alpha_factory/write_df.py
alpha_factory/data/functions.csv
alpha_factory-0.3.6.dist-info/DESCRIPTION.rst
alpha_factory-0.3.6.dist-info/METADATA
alpha_factory-0.3.6.dist-info/RECORD
alpha_factory-0.3.6.dist-info/WHEEL
alpha_factory-0.3.6.dist-info/metadata.json
alpha_factory-0.3.6.dist-info/top_level.txt
