Metadata-Version: 2.0
Name: alpha-factory
Version: 0.3.6
Summary: generate alpha factors
Home-page: UNKNOWN
Author: Yili Peng
Author-email: yili_peng@outlook.com
License: UNKNOWN
Platform: UNKNOWN
Requires-Dist: RNWS (>=0.2.1)
Requires-Dist: alphalens
Requires-Dist: data-box
Requires-Dist: empyrical
Requires-Dist: single-factor-model (>=0.3.2)
